{
  "name": "ModList",
  "description": "Displays your installed mods inside the game and gives you a warning prompt upon starting the game to tell you if a mod failed to load.",
  "id": "mod-list",
  "version": "0.2.2",
  "author": "Lauriethefish",
  "authorIcon": "https://avatars.githubusercontent.com/u/176073241?v=4",
  "modloader": "Scotland2",
  "download": "https://github.com/DanTheMan827-BeatSaber/Quest.ModList/releases/download/v0.2.2/ModList.qmod",
  "dependencies": [
    {
      "id": "beatsaber-hook",
      "version": "^6.4.1"
    },
    {
      "id": "bsml",
      "version": "^0.4.51"
    },
    {
      "id": "custom-types",
      "version": "^0.18.2"
    },
    {
      "id": "paper2_scotland2",
      "version": "^4.6.1"
    }
  ],
  "source": "https://github.com/DanTheMan827-BeatSaber/Quest.ModList/",
  "cover": "https://raw.githubusercontent.com/DanTheMan827-BeatSaber/Quest.ModList/main/cover.jpg",
  "funding": [],
  "website": "https://github.com/DanTheMan827-BeatSaber/Quest.ModList/"
}
