{
  "name": "PeripheralHUD",
  "description": "Move your in-game HUD into your peripheral vision, allowing for easy at-a-glance viewing of your combo, score, etc!",
  "id": "peripheralhud",
  "version": "1.1.1",
  "author": "Kaitlyn",
  "authorIcon": "https://avatars.githubusercontent.com/u/87990853?v=4",
  "modloader": "QuestLoader",
  "download": "https://github.com/whatdahopper/PeripheralHUD/releases/download/v1.1.1/peripheralhud_v1.1.1.qmod",
  "dependencies": [
    {
      "id": "codegen",
      "version": "=0.32.0"
    },
    {
      "id": "custom-types",
      "version": "=0.15.22"
    },
    {
      "id": "questui",
      "version": "=0.17.10"
    }
  ],
  "source": "https://github.com/whatdahopper/PeripheralHUD/",
  "cover": "https://raw.githubusercontent.com/whatdahopper/PeripheralHUD/main/cover.png",
  "funding": [],
  "website": null
}
