{
  "name": "FuckMaps",
  "description": "This mod crashes your game if you play a song below or above a configurable BPM.",
  "id": "fuckmaps",
  "version": "1.0.0",
  "author": "rui2015",
  "authorIcon": "https://avatars.githubusercontent.com/u/15705566?v=4",
  "modloader": "QuestLoader",
  "download": "https://github.com/FranciscoRibeiro03/FuckMaps/releases/download/v1.0.0/FuckMaps.qmod",
  "dependencies": [],
  "source": "https://github.com/FranciscoRibeiro03/FuckMaps/",
  "cover": null,
  "funding": [],
  "website": null
}
