{
  "name": "PinkCore",
  "description": "PinkCore is a core mod that ports over the rest of SongCore's features.\nThis includes adding information to your game such as Mappers names, Mod Requirements, Custom Colours, Custom Difficulty names, Burn Marks, and more!",
  "id": "pinkcore",
  "version": "1.9.0",
  "author": "RedBrumbler, Pink, StackDoubleFlow, Lillie, darknight1050",
  "authorIcon": "https://avatars.githubusercontent.com/u/62712899?v=4",
  "modloader": "Scotland2",
  "download": "https://github.com/ModdingPink/PinkCore/releases/download/v1.9.0/PinkCore.qmod",
  "dependencies": [
    {
      "id": "bsml",
      "version": "^0.4.0"
    },
    {
      "id": "custom-types",
      "version": "^0.16.0"
    },
    {
      "id": "songloader",
      "version": "^0.11.0"
    }
  ],
  "source": "https://github.com/ModdingPink/PinkCore/",
  "cover": "https://raw.githubusercontent.com/ModdingPink/PinkCore/master/cover.png",
  "funding": [],
  "website": "https://github.com/ModdingPink/PinkCore/"
}
